README.rst
setup.py
django_template_finder.egg-info/PKG-INFO
django_template_finder.egg-info/SOURCES.txt
django_template_finder.egg-info/dependency_links.txt
django_template_finder.egg-info/not-zip-safe
django_template_finder.egg-info/top_level.txt
templatefinder/__init__.py
templatefinder/tests.py
templatefinder/utils.py
templatefinder/test_project/__init__.py
templatefinder/test_project/urls.py
templatefinder/test_project/wsgi.py
templatefinder/test_project/testapp/__init__.py
templatefinder/test_project/testapp/models.py