Metadata-Version: 1.1
Name: django-template-finder
Version: 0.5
Summary: Simple Django utility that allows you to find templates with names matching given pattern
Home-page: https://github.com/TyMaszWeb/django-template-finder
Author: Piotr Kilczuk
Author-email: piotr@tymaszweb.pl
License: BSD License
Platform: OS Independent
Classifier: Development Status :: 4 - Beta
Classifier: Environment :: Web Environment
Classifier: Framework :: Django
Classifier: Intended Audience :: Developers
Classifier: License :: OSI Approved :: BSD License
Classifier: Operating System :: OS Independent
Classifier: Programming Language :: Python
Classifier: Topic :: Internet :: WWW/HTTP
